[
  {
    "id": 2,
    "en": "spark",
    "ja": "火花，きらめき"
  },
  {
    "id": 52,
    "en": "meantime",
    "ja": "合間に，その間に"
  },
  {
    "id": 102,
    "en": "beggar",
    "ja": "乞食，物乞い"
  },
  {
    "id": 152,
    "en": "fortunately",
    "ja": "運よく，幸いにも"
  },
  {
    "id": 202,
    "en": "deflate",
    "ja": "空気を抜く，しぼませる"
  },
  {
    "id": 252,
    "en": "scoop up",
    "ja": "すくい取る，くみ上げる"
  },
  {
    "id": 302,
    "en": "efficiency",
    "ja": "効率，能率"
  },
  {
    "id": 352,
    "en": "restrain",
    "ja": "抑える"
  },
  {
    "id": 402,
    "en": "pronounce",
    "ja": "を発音する"
  },
  {
    "id": 452,
    "en": "thoroughly",
    "ja": "徹底的に，完全に"
  },
  {
    "id": 502,
    "en": "capitalism",
    "ja": "資本主義"
  },
  {
    "id": 552,
    "en": "sole",
    "ja": "単独の"
  },
  {
    "id": 602,
    "en": "anticipate",
    "ja": "を期待する，予想する"
  },
  {
    "id": 652,
    "en": "in token of",
    "ja": "の証拠に，のしるしとして"
  },
  {
    "id": 702,
    "en": "immensely",
    "ja": "莫大に，広大に"
  },
  {
    "id": 752,
    "en": "steer",
    "ja": "を操縦する，かじを取る"
  },
  {
    "id": 802,
    "en": "uncommon",
    "ja": "珍しい，滅多にない"
  },
  {
    "id": 852,
    "en": "in anticipation of",
    "ja": "を予期して，見込んで"
  },
  {
    "id": 902,
    "en": "portray",
    "ja": "描く，表現する"
  },
  {
    "id": 952,
    "en": "intensity",
    "ja": "強度，強烈さ"
  },
  {
    "id": 1002,
    "en": "attentive",
    "ja": "注意深い"
  },
  {
    "id": 1052,
    "en": "astronaut",
    "ja": "宇宙飛行士"
  },
  {
    "id": 1102,
    "en": "alongside",
    "ja": "と一緒に，並行して"
  },
  {
    "id": 1152,
    "en": "illegal",
    "ja": "違法な，不法な"
  },
  {
    "id": 1202,
    "en": "classify",
    "ja": "に分類する，類別する"
  },
  {
    "id": 1252,
    "en": "fable",
    "ja": "作り話"
  },
  {
    "id": 1302,
    "en": "trivial",
    "ja": "取るに足らない"
  },
  {
    "id": 1352,
    "en": "parliamentary",
    "ja": "議会の"
  },
  {
    "id": 1402,
    "en": "reap",
    "ja": "を収穫する，刈る"
  },
  {
    "id": 1452,
    "en": "dual citizenship",
    "ja": "二重国籍，二重国籍者"
  },
  {
    "id": 1502,
    "en": "elastic",
    "ja": "弾力のある，伸縮自在の"
  },
  {
    "id": 1552,
    "en": "detergent",
    "ja": "洗剤"
  },
  {
    "id": 1602,
    "en": "giggle",
    "ja": "くすくす笑う"
  },
  {
    "id": 1652,
    "en": "discomfort",
    "ja": "不快感，違和感"
  },
  {
    "id": 1702,
    "en": "frightful",
    "ja": "恐ろしい"
  },
  {
    "id": 1752,
    "en": "splendor",
    "ja": "輝き"
  },
  {
    "id": 1802,
    "en": "cherish",
    "ja": "大切にする，希望を抱く"
  },
  {
    "id": 1852,
    "en": "foggy",
    "ja": "霧のかかった"
  },
  {
    "id": 1902,
    "en": "believe in",
    "ja": "を信じる，を信用する"
  },
  {
    "id": 1952,
    "en": "pollute",
    "ja": "汚染する"
  },
  {
    "id": 2002,
    "en": "mother-in-law",
    "ja": "義理の母，義母"
  },
  {
    "id": 2052,
    "en": "amid",
    "ja": "真ん中に，の中に"
  },
  {
    "id": 2102,
    "en": "retailer",
    "ja": "小売業者"
  },
  {
    "id": 2152,
    "en": "hitch",
    "ja": "引っかける"
  },
  {
    "id": 2202,
    "en": "treacherous",
    "ja": "裏切った，反逆の"
  },
  {
    "id": 2252,
    "en": "retort",
    "ja": "言い返す"
  },
  {
    "id": 2302,
    "en": "par",
    "ja": "同等，等価"
  },
  {
    "id": 2352,
    "en": "glaze",
    "ja": "上塗りする"
  },
  {
    "id": 2402,
    "en": "abbreviate",
    "ja": "を略する，短縮する"
  },
  {
    "id": 2452,
    "en": "monopolize",
    "ja": "を独占する"
  },
  {
    "id": 2502,
    "en": "crack up",
    "ja": "大破する，くじける"
  },
  {
    "id": 2552,
    "en": "insincere",
    "ja": "誠意のない，不誠実な"
  },
  {
    "id": 2602,
    "en": "feudal",
    "ja": "領地の，封建の"
  },
  {
    "id": 2652,
    "en": "crest",
    "ja": "とさか"
  },
  {
    "id": 2702,
    "en": "neutralize",
    "ja": "中和する"
  },
  {
    "id": 2752,
    "en": "mimic",
    "ja": "を模倣する，真似る"
  },
  {
    "id": 2802,
    "en": "tangible",
    "ja": "有形の，手で触れる"
  },
  {
    "id": 2852,
    "en": "depot",
    "ja": "停車場"
  },
  {
    "id": 2902,
    "en": "squeak",
    "ja": "きしむ"
  },
  {
    "id": 2952,
    "en": "tactic",
    "ja": "戦術"
  },
  {
    "id": 3002,
    "en": "dehydrate",
    "ja": "脱水する，水を抜く"
  },
  {
    "id": 3052,
    "en": "grumpy",
    "ja": "気難しい"
  },
  {
    "id": 3102,
    "en": "accompany",
    "ja": "に付き添う，に同行する"
  },
  {
    "id": 3152,
    "en": "resolve",
    "ja": "解決する，を決心する"
  },
  {
    "id": 3202,
    "en": "alliance",
    "ja": "同盟，協定"
  },
  {
    "id": 3252,
    "en": "abstract",
    "ja": "抽象的な，非具体的な"
  },
  {
    "id": 3302,
    "en": "stature",
    "ja": "身長，身の丈"
  },
  {
    "id": 3352,
    "en": "bankrupt",
    "ja": "破産"
  }
]