[
  {
    "id": 45,
    "en": "dosage",
    "ja": "投与量，服用量"
  },
  {
    "id": 95,
    "en": "in person",
    "ja": "直接に，対面で"
  },
  {
    "id": 145,
    "en": "integrate",
    "ja": "統合する，一体化する"
  },
  {
    "id": 195,
    "en": "multinational",
    "ja": "多国籍の，複数の国籍からなる"
  },
  {
    "id": 245,
    "en": "diagnosis",
    "ja": "診断，判断"
  },
  {
    "id": 295,
    "en": "comparable",
    "ja": "比較できる，比べられる"
  },
  {
    "id": 345,
    "en": "interact",
    "ja": "相互作用する，互いに影響を与える"
  },
  {
    "id": 395,
    "en": "bounce back",
    "ja": "持ち直す，回復する"
  },
  {
    "id": 445,
    "en": "nutrient",
    "ja": "栄養素，栄養分"
  },
  {
    "id": 495,
    "en": "signify",
    "ja": "意味する，示す"
  },
  {
    "id": 545,
    "en": "endear",
    "ja": "慕わせる，愛される"
  },
  {
    "id": 595,
    "en": "shake up",
    "ja": "大きく変える，再編する"
  },
  {
    "id": 645,
    "en": "treason",
    "ja": "反逆，反乱"
  },
  {
    "id": 695,
    "en": "curtail",
    "ja": "削減する，減少させる"
  },
  {
    "id": 745,
    "en": "ferocious",
    "ja": "どう猛な，激しい"
  },
  {
    "id": 795,
    "en": "exhilarate",
    "ja": "陽気にさせる，楽しくさせる"
  },
  {
    "id": 845,
    "en": "sag",
    "ja": "たるむ，弛む"
  },
  {
    "id": 895,
    "en": "corrupt",
    "ja": "不正行為をする，カンニングする"
  },
  {
    "id": 945,
    "en": "wince",
    "ja": "ひるむ，後退する"
  },
  {
    "id": 995,
    "en": "screech",
    "ja": "金切り声，高い叫び声"
  },
  {
    "id": 1045,
    "en": "efficacy",
    "ja": "効能，効果"
  },
  {
    "id": 1095,
    "en": "ark",
    "ja": "箱舟，ノアの方舟"
  },
  {
    "id": 1145,
    "en": "lock in",
    "ja": "を閉じ込める，隔離する"
  },
  {
    "id": 1195,
    "en": "sire",
    "ja": "雄親，父親"
  },
  {
    "id": 1245,
    "en": "insurgency",
    "ja": "反乱，反乱軍"
  },
  {
    "id": 1295,
    "en": "implacable",
    "ja": "和解しにくい，対立しやすい"
  },
  {
    "id": 1345,
    "en": "gasp",
    "ja": "息をのむ"
  },
  {
    "id": 1395,
    "en": "whimsical",
    "ja": "気まぐれな，移り気な"
  },
  {
    "id": 1445,
    "en": "devoid",
    "ja": "欠けている，不足している"
  },
  {
    "id": 1495,
    "en": "intimately",
    "ja": "親密に，密接に"
  },
  {
    "id": 1545,
    "en": "insofar",
    "ja": "その範囲で，その限りで"
  },
  {
    "id": 1595,
    "en": "debase",
    "ja": "堕落させる，道を踏み外させる"
  },
  {
    "id": 1645,
    "en": "frankly speaking",
    "ja": "率直に言うと，はっきりと言って，正直に言って，素直に言えば"
  },
  {
    "id": 1695,
    "en": "secession",
    "ja": "離脱，退出すること"
  },
  {
    "id": 1745,
    "en": "diaper",
    "ja": "おむつ，おしめ"
  },
  {
    "id": 1795,
    "en": "banter",
    "ja": "冗談，笑い話，おどけ"
  },
  {
    "id": 1845,
    "en": "disintegration",
    "ja": "崩壊，崩壊状態"
  },
  {
    "id": 1895,
    "en": "funk",
    "ja": "臆病，怯える，気が小さい"
  },
  {
    "id": 1945,
    "en": "absentee",
    "ja": "欠席者，不参加者"
  },
  {
    "id": 1995,
    "en": "nuptial",
    "ja": "婚礼の"
  },
  {
    "id": 2045,
    "en": "categorize A as B",
    "ja": "AをBの範疇に分ける，AをBとして分類する"
  },
  {
    "id": 2095,
    "en": "accentuate",
    "ja": "強調する"
  },
  {
    "id": 2145,
    "en": "affable",
    "ja": "親しみの持てる"
  },
  {
    "id": 2195,
    "en": "flimsy",
    "ja": "薄っぺらな"
  },
  {
    "id": 2245,
    "en": "exploratory",
    "ja": "探検の"
  },
  {
    "id": 2295,
    "en": "donate A to B",
    "ja": "AをBに寄付する，AをBに寄贈する"
  },
  {
    "id": 2345,
    "en": "mortuary",
    "ja": "遺体"
  },
  {
    "id": 2395,
    "en": "frugality",
    "ja": "倹約"
  },
  {
    "id": 2445,
    "en": "bromide",
    "ja": "臭化物"
  },
  {
    "id": 2495,
    "en": "take A for granted",
    "ja": "Aを当然と思う，Aを当たり前と考える"
  },
  {
    "id": 2545,
    "en": "pick up the pieces",
    "ja": "欠片を拾う，事態を修復する"
  },
  {
    "id": 2595,
    "en": "caprice",
    "ja": "気まぐれ"
  },
  {
    "id": 2645,
    "en": "ascribe A to B",
    "ja": "AからBに帰する"
  },
  {
    "id": 2695,
    "en": "chlorine",
    "ja": "塩素"
  },
  {
    "id": 2745,
    "en": "husk",
    "ja": "殻"
  },
  {
    "id": 2795,
    "en": "demure",
    "ja": "控えめな"
  },
  {
    "id": 2845,
    "en": "wash up",
    "ja": "顔や手を洗う，皿洗いをする"
  },
  {
    "id": 2895,
    "en": "let off",
    "ja": "降ろす，放つ"
  },
  {
    "id": 2945,
    "en": "pedantic",
    "ja": "学者ぶった"
  },
  {
    "id": 2995,
    "en": "drink to",
    "ja": "を祝って飲む，偲んで酒を飲む"
  },
  {
    "id": 3045,
    "en": "despondent",
    "ja": "落胆した"
  },
  {
    "id": 3095,
    "en": "stratum",
    "ja": "地層"
  },
  {
    "id": 3145,
    "en": "admonition",
    "ja": "訓戒"
  },
  {
    "id": 3195,
    "en": "pout",
    "ja": "口をとがらせる"
  },
  {
    "id": 3245,
    "en": "notify A of B",
    "ja": "AにBを通知する"
  },
  {
    "id": 3295,
    "en": "teeter",
    "ja": "ぶらぶらする"
  },
  {
    "id": 3345,
    "en": "fart",
    "ja": "おならをする"
  },
  {
    "id": 3395,
    "en": "sojourn",
    "ja": "短期滞在する"
  },
  {
    "id": 3445,
    "en": "run errands",
    "ja": "使い走りをする，お使いをする"
  },
  {
    "id": 3495,
    "en": "extortion",
    "ja": "恐喝"
  },
  {
    "id": 3545,
    "en": "fissure",
    "ja": "亀裂"
  },
  {
    "id": 3595,
    "en": "kindred",
    "ja": "親族，家族"
  },
  {
    "id": 3645,
    "en": "stumbling block",
    "ja": "障害，障害物"
  },
  {
    "id": 3695,
    "en": "kiln",
    "ja": "窯"
  },
  {
    "id": 3745,
    "en": "come in handy",
    "ja": "助けになる，便利な"
  },
  {
    "id": 3795,
    "en": "come up with",
    "ja": "を思いつく，を考え出す"
  },
  {
    "id": 3845,
    "en": "up for grabs",
    "ja": "容易に手に入る，誰が勝つかわからない"
  },
  {
    "id": 3895,
    "en": "roll out",
    "ja": "製品投入する，水平展開する"
  },
  {
    "id": 3945,
    "en": "insist on",
    "ja": "を主張する，を要求する"
  },
  {
    "id": 3995,
    "en": "opulent",
    "ja": "豊富な"
  },
  {
    "id": 4045,
    "en": "snippet",
    "ja": "切れ端"
  },
  {
    "id": 4095,
    "en": "put up with",
    "ja": "我慢する，耐える"
  },
  {
    "id": 4145,
    "en": "brush aside",
    "ja": "無視する，軽視する"
  },
  {
    "id": 4195,
    "en": "ignominy",
    "ja": "恥辱，不名誉"
  },
  {
    "id": 4245,
    "en": "palliate",
    "ja": "緩和する，軽減する"
  }
]